envkey/__init__.py
envkey/fetch.py
envkey/loader.py
envkey/ext/.DS_Store
envkey/ext/envkey-fetch_darwin_amd64/envkey-fetch
envkey/ext/envkey-fetch_freebsd_amd64/envkey-fetch
envkey/ext/envkey-fetch_linux_amd64/envkey-fetch
envkey/ext/envkey-fetch_windows_amd64/envkey-fetch.exe
darcy_bingley_wickham-0.0.8.dist-info/LICENSE.txt
darcy_bingley_wickham-0.0.8.dist-info/METADATA
darcy_bingley_wickham-0.0.8.dist-info/WHEEL
darcy_bingley_wickham-0.0.8.dist-info/top_level.txt
darcy_bingley_wickham-0.0.8.dist-info/RECORD
