Metadata-Version: 2.1
Name: darcy-bingley-wickham
Version: 0.0.8
Summary: publish testing package - do not use
Home-page: https://github.com/org2321/reponame
Author: EnvKey
Author-email: support@envkey.com
License: MIT
Keywords: security,secrets management,configuration management,environment variables,configuration,python
Platform: UNKNOWN
Classifier: Development Status :: 5 - Production/Stable
Classifier: Intended Audience :: Developers
Classifier: Intended Audience :: System Administrators
Classifier: License :: OSI Approved :: MIT License
Classifier: Programming Language :: Python :: 2
Classifier: Programming Language :: Python :: 3
Classifier: Topic :: Security
Classifier: Topic :: Security :: Cryptography
Requires-Dist: python-dotenv (>=0.13.0)
